gbdny/Binomialdistribution.py
gbdny/Gaussiandistribution.py
gbdny/Generaldistribution.py
gbdny/__init__.py
gbdny-0.0.2.dist-info/LICENSE
gbdny-0.0.2.dist-info/METADATA
gbdny-0.0.2.dist-info/WHEEL
gbdny-0.0.2.dist-info/top_level.txt
gbdny-0.0.2.dist-info/RECORD
