Metadata-Version: 2.1
Name: gbdny
Version: 0.0.2
Summary: A small example package for gaussian and binomial distributions.
Home-page: UNKNOWN
Author: Nicolas Yanez
Author-email: n.yanez615@gmail.com
License: UNKNOWN
Platform: UNKNOWN
Classifier: Programming Language :: Python :: 3
Classifier: License :: OSI Approved :: MIT License
Classifier: Operating System :: OS Independent
Requires-Python: >=3.6
